metametameta/__about__.py
metametameta/__init__.py
metametameta/__main__.py
metametameta/filesystem.py
metametameta/find.py
metametameta/find_it.py
metametameta/from_importlib.py
metametameta/from_pep621.py
metametameta/from_poetry.py
metametameta/from_setup_cfg.py
metametameta/from_setup_py.py
metametameta/general.py
metametameta/known.py
metametameta/logging_config.py
metametameta/py.typed
metametameta/utils/__init__.py
metametameta/utils/cli_suggestions.py
metametameta-0.1.4.dist-info/METADATA
metametameta-0.1.4.dist-info/WHEEL
metametameta-0.1.4.dist-info/entry_points.txt
metametameta-0.1.4.dist-info/licenses/LICENSE
metametameta-0.1.4.dist-info/RECORD
