Metadata-Version: 2.4
Name: metametameta
Version: 0.1.4
Summary: Generate __about__.py with dunder meta.
License: MIT
License-File: LICENSE
Keywords: packaging,metadata
Author: Matthew Martin
Author-email: matthewdeanmartin@gmail.com
Requires-Python: >=3.8,<4.0
Classifier: Development Status :: 4 - Beta
Classifier: Intended Audience :: Developers
Classifier: License :: OSI Approved :: MIT License
Classifier: Operating System :: OS Independent
Classifier: Programming Language :: Python
Classifier: Programming Language :: Python :: 3
Classifier: Programming Language :: Python :: 3.8
Classifier: Programming Language :: Python :: 3.9
Classifier: Programming Language :: Python :: 3.10
Classifier: Programming Language :: Python :: 3.11
Classifier: Programming Language :: Python :: 3.12
Classifier: Programming Language :: Python :: 3.13
Classifier: Programming Language :: Python :: 3.14
Requires-Dist: colorlog (>=6.9.0)
Requires-Dist: rich_argparse
Requires-Dist: toml (>=0.10.2)
Project-URL: Bug Tracker, https://github.com/matthewdeanmartin/metametameta/issues
Project-URL: Change Log, https://github.com/matthewdeanmartin/metametameta/blob/main/CHANGELOG.md
Project-URL: Documentation, https://matthewdeanmartin.github.io/metametameta/metametameta/index.html
Project-URL: Homepage, https://github.com/matthewdeanmartin/metametameta
Project-URL: Repository, https://github.com/matthewdeanmartin/metametameta
